swissarmyknife/__init__.py
swissarmyknife/file_handling.py
swissarmyknife-0.1.0.dist-info/LICENSE.txt
swissarmyknife-0.1.0.dist-info/METADATA
swissarmyknife-0.1.0.dist-info/WHEEL
swissarmyknife-0.1.0.dist-info/top_level.txt
swissarmyknife-0.1.0.dist-info/RECORD
