Metadata-Version: 2.1
Name: swissarmyknife
Version: 0.1.0
Summary: A few functions often used
Home-page: https://github.com/schrma/swissarmyknife
Author: mm4go
Author-email: mm4go.marcschr@dfgh.net
License: MIT
Project-URL: Documentation, https://swissarmyknife.readthedocs.io/en/latest/
Project-URL: Source, https://github.com/schrma/swissarmyknife
Platform: any
Classifier: Development Status :: 4 - Beta
Classifier: Programming Language :: Python
License-File: LICENSE.txt
Requires-Dist: parse
Requires-Dist: importlib-metadata ; python_version < "3.8"
Provides-Extra: testing
Requires-Dist: setuptools ; extra == 'testing'
Requires-Dist: pytest ; extra == 'testing'
Requires-Dist: pytest-cov ; extra == 'testing'
Requires-Dist: pylint ; extra == 'testing'
Requires-Dist: flake8 ; extra == 'testing'
Requires-Dist: mock ; extra == 'testing'
